{"id":1,"name":"Lindsay","email":"domelindsay@gmail.com","birthday":[4,11,2003]}
{"id":2,"name":"2","email":"2","birthday":[12,9,2000]}
{"id":6,"name":"6","email":"6","birthday":[6,6,2006]}
{"id":7,"name":"few","email":"fse","birthday":[7,7,2007]}
{"id":9,"name":"99999999","email":"9999999","birthday":[9,9,2009]}
{"id":8,"name":"8888888","email":"8888888888","birthday":[8,8,2008]}
{"id":10,"name":"10","email":"10","birthday":[10,10,2010]}
{"id":12,"name":"12","email":"12","birthday":[12,12,2012]}
{"id":13,"name":"13","email":"13","birthday":[3,3,2003]}
